LICENSE
README.md
setup.py
pwnpy/__init__.py
pwnpy/__main__.py
pwnpy.egg-info/PKG-INFO
pwnpy.egg-info/SOURCES.txt
pwnpy.egg-info/dependency_links.txt
pwnpy.egg-info/entry_points.txt
pwnpy.egg-info/requires.txt
pwnpy.egg-info/top_level.txt
pwnpy/libs/Manager.py
pwnpy/libs/Static.py
pwnpy/libs/__init__.py
pwnpy/modules/BT.py
pwnpy/modules/Font.ttc
pwnpy/modules/GPS.py
pwnpy/modules/UI.py
pwnpy/modules/WebUI.py
pwnpy/modules/WiFi.py