Metadata-Version: 2.1
Name: pwnpy
Version: 1.53
Summary: wardriving tool
Home-page: https://github.com/nbdy/pwnpy
Author: Pascal Eberlein
Author-email: pascal@eberlein.io
License: UNKNOWN
Keywords: wardriving tool raspberry pi
Platform: UNKNOWN
Classifier: Intended Audience :: Developers
Classifier: Topic :: Software Development :: Build Tools
Classifier: License :: OSI Approved :: MIT License
License-File: LICENSE
